usdm_bc_mapper/__init__.py
usdm_bc_mapper/_types.py
usdm_bc_mapper/cdisc_bc_search.py
usdm_bc_mapper/cli.py
usdm_bc_mapper/find_bc.py
usdm_bc_mapper/llm.py
usdm_bc_mapper/mapper.py
usdm_bc_mapper/settings.py
usdm_bc_mapper/data/Thesaurus.txt
usdm_bc_mapper/data/cdisc_biomedical_concepts_latest.csv
usdm_bc_mapper/data/cdisc_sdtm_dataset_specializations_latest.csv
usdm_bc_mapper/data/system_prompt.txt
usdm_bc_mapper/data/cdisc_terminology/ADaM Terminology.txt
usdm_bc_mapper/data/cdisc_terminology/CDASH Terminology.txt
usdm_bc_mapper/data/cdisc_terminology/DDF Terminology.txt
usdm_bc_mapper/data/cdisc_terminology/Protocol Terminology.txt
usdm_bc_mapper/data/cdisc_terminology/SDTM Terminology.txt
usdm_bc_mapper/data/cdisc_terminology/SEND Terminology.txt
usdm_bc_mapper-0.3.2.dist-info/METADATA
usdm_bc_mapper-0.3.2.dist-info/WHEEL
usdm_bc_mapper-0.3.2.dist-info/entry_points.txt
usdm_bc_mapper-0.3.2.dist-info/licenses/LICENSE
usdm_bc_mapper-0.3.2.dist-info/RECORD
