Metadata-Version: 2.4
Name: usdm-bc-mapper
Version: 0.3.2
Summary: A tool to convert activities into biomedical concepts
Author-email: Pritam Dey <pritamdey@ailens.ai>, Chaitanya Pradeep Repaka <rchpradeep@ailens.ai>, Chekresh Hosbekt <chekresh.hosbect@ailens.ai>
License-File: LICENSE
Requires-Python: >=3.13
Requires-Dist: bm25s>=0.2.13
Requires-Dist: cyclopts>=3.23.0
Requires-Dist: jinja2>=3.1.6
Requires-Dist: openai>=1.101.0
Requires-Dist: polars>=1.33.0
Requires-Dist: pydantic-settings>=2.10.1
Requires-Dist: pystemmer>=3.0.0
Requires-Dist: tqdm>=4.67.1
Requires-Dist: usdm>=0.64.0
